setup.py
riseml/__init__.py
riseml/__main__.py
riseml/config_parser.py
riseml/server.py
riseml.egg-info/PKG-INFO
riseml.egg-info/SOURCES.txt
riseml.egg-info/dependency_links.txt
riseml.egg-info/entry_points.txt
riseml.egg-info/requires.txt
riseml.egg-info/top_level.txt
riseml/client/__init__.py
riseml/client/api_client.py
riseml/client/configuration.py
riseml/client/rest.py
riseml/client/apis/__init__.py
riseml/client/apis/admin_api.py
riseml/client/apis/default_api.py
riseml/client/models/__init__.py
riseml/client/models/changeset.py
riseml/client/models/error.py
riseml/client/models/job.py
riseml/client/models/repository.py
riseml/client/models/scratch_entry.py
riseml/client/models/user.py