Metadata-Version: 1.0
Name: riseml
Version: 0.3.7
Summary: RiseML API client
Home-page: https://riseml.com
Author: UNKNOWN
Author-email: contact@riseml.com
License: UNKNOWN
Keywords: RiseML
Platform: UNKNOWN
